clir/__init__.py
clir/cli.py
clir/command.py
clir/config/__init__.py
clir/config/clir.conf
clir/config/db/__init__.py
clir/config/db/schema.sql
clir/utils/__init__.py
clir/utils/config.py
clir/utils/core.py
clir/utils/db.py
clir/utils/filters.py
clir-0.8.3.dist-info/LICENSE
clir-0.8.3.dist-info/METADATA
clir-0.8.3.dist-info/WHEEL
clir-0.8.3.dist-info/entry_points.txt
clir-0.8.3.dist-info/RECORD
