Metadata-Version: 2.3
Name: clir
Version: 0.8.3
Summary: A clear and fast way to store and recover your commands
License: MIT
Author: Elkin Aguas
Author-email: elkinaguas@gmail.com
Requires-Python: >=3.8,<4.0
Classifier: License :: OSI Approved :: MIT License
Classifier: Programming Language :: Python :: 3
Classifier: Programming Language :: Python :: 3.8
Classifier: Programming Language :: Python :: 3.9
Classifier: Programming Language :: Python :: 3.10
Classifier: Programming Language :: Python :: 3.11
Classifier: Programming Language :: Python :: 3.12
Classifier: Programming Language :: Python :: 3.13
Requires-Dist: click (>=8.1.7,<9.0.0)
Requires-Dist: rich (>=13.5.2,<14.0.0)
Requires-Dist: rich-click (>=1.7.0,<2.0.0)
Requires-Dist: textual (>=0.47.1,<0.48.0)
Project-URL: Bug Tracker, https://github.com/elkinaguas/clir/issues
Project-URL: Homepage, https://github.com/elkinaguas/clir
Project-URL: Repository, https://github.com/elkinaguas/clir
